prompt_optimizer/__init__.py
prompt_optimizer/cli/__init__.py
prompt_optimizer/cli/main.py
prompt_optimizer/metric/__init__.py
prompt_optimizer/metric/base.py
prompt_optimizer/metric/bertscore_metric.py
prompt_optimizer/metric/token_metric.py
prompt_optimizer/poptim/__init__.py
prompt_optimizer/poptim/autocorrect_optim.py
prompt_optimizer/poptim/base.py
prompt_optimizer/poptim/entropy_optim.py
prompt_optimizer/poptim/lemmatizer_optim.py
prompt_optimizer/poptim/logger.py
prompt_optimizer/poptim/name_replace_optim.py
prompt_optimizer/poptim/pulp_optim.py
prompt_optimizer/poptim/punctuation_optim.py
prompt_optimizer/poptim/sequential.py
prompt_optimizer/poptim/stemmer_optim.py
prompt_optimizer/poptim/stop_word_optim.py
prompt_optimizer/poptim/synonym_replace_optim.py
prompt_optimizer/poptim/utils.py
prompt_optimizer/visualize/__init__.py
prompt_optimizer/visualize/stringdiffer.py
prompt_optimizer-0.2.1.dist-info/LICENSE
prompt_optimizer-0.2.1.dist-info/METADATA
prompt_optimizer-0.2.1.dist-info/WHEEL
prompt_optimizer-0.2.1.dist-info/entry_points.txt
prompt_optimizer-0.2.1.dist-info/RECORD
