Metadata-Version: 2.1
Name: prompt-optimizer
Version: 0.2.1
Summary: 
Author: Vaibhav Kumar
Author-email: 34630911+TimeTraveller-San@users.noreply.github.com
Requires-Python: >=3.8.1,<4.0
Classifier: Programming Language :: Python :: 3
Classifier: Programming Language :: Python :: 3.9
Classifier: Programming Language :: Python :: 3.10
Classifier: Programming Language :: Python :: 3.11
Requires-Dist: autocorrect (>=2.6.1,<3.0.0)
Requires-Dist: black (>=23.3.0,<24.0.0)
Requires-Dist: isort (>=5.12.0,<6.0.0)
Requires-Dist: nltk (>=3.8.1,<4.0.0)
Requires-Dist: pulp (>=2.7.0,<3.0.0)
Requires-Dist: tiktoken (>=0.3.3,<0.4.0)
Requires-Dist: torch (>=2.0.0,<3.0.0)
Requires-Dist: transformers (>=4.27.4,<5.0.0)
